mheatmap/__init__.py
mheatmap/_amc_postprocess.py
mheatmap/_rms_permute.py
mheatmap/constants.py
mheatmap/matrix.py
mheatmap/graph/__init__.py
mheatmap/graph/_copermute_from_bipermute.py
mheatmap/graph/_spectral_permute.py
mheatmap/graph/_two_walk_laplacian.py
mheatmap/utils/__init__.py
mheatmap/utils/_base.py
mheatmap/utils/plot_bipartite_confusion_matrix.py
mheatmap/utils/plot_eigen.py
mheatmap-1.2.5.dist-info/licenses/LICENSE
mheatmap-1.2.5.dist-info/METADATA
mheatmap-1.2.5.dist-info/WHEEL
mheatmap-1.2.5.dist-info/top_level.txt
mheatmap-1.2.5.dist-info/RECORD
