Metadata-Version: 2.4
Name: mheatmap
Version: 1.2.5
Summary: A package for mosaic/proportional heatmap visualization and matrix analysis
Author-email: Juntang Wang <jw853@duke.edu>
License-Expression: MIT
Project-URL: Homepage, https://github.com/qqgjyx/mheatmap
Project-URL: Bug Tracker, https://github.com/qqgjyx/mheatmap/issues
Classifier: Programming Language :: Python :: 3
Classifier: Operating System :: OS Independent
Requires-Python: >=3.8
License-File: LICENSE
Requires-Dist: numpy
Requires-Dist: matplotlib
Requires-Dist: seaborn
Requires-Dist: scipy
Requires-Dist: scikit-learn
Provides-Extra: dev
Requires-Dist: pytest>=7.0; extra == "dev"
Requires-Dist: pytest-cov>=4.0; extra == "dev"
Dynamic: license-file
